log_to_slack/__init__.py
log_to_slack-1.8.1.dist-info/LICENSE
log_to_slack-1.8.1.dist-info/METADATA
log_to_slack-1.8.1.dist-info/WHEEL
log_to_slack-1.8.1.dist-info/top_level.txt
log_to_slack-1.8.1.dist-info/RECORD
