Metadata-Version: 2.1
Name: log-to-slack
Version: 1.8.1
Summary: Posts log events to Slack via API
Home-page: https://github.com/pandianmn/log_to_slack
Download-URL: https://github.com/pandianmn/log_to_slack/archive/1.8.1.tar.gz
Author: Pandian Muninathan
Author-email: pandian.m@hotmail.com
Keywords: slack,logging
Classifier: Development Status :: 5 - Production/Stable
Classifier: Environment :: Web Environment
Classifier: Framework :: Django
Classifier: Intended Audience :: Developers
Classifier: Intended Audience :: System Administrators
Classifier: License :: OSI Approved :: Apache Software License
Classifier: Natural Language :: English
Classifier: Operating System :: OS Independent
Classifier: Programming Language :: Python
Classifier: Programming Language :: Python :: 2
Classifier: Programming Language :: Python :: 3
Classifier: Topic :: Communications :: Chat
Classifier: Topic :: Office/Business :: Groupware
License-File: LICENSE
Requires-Dist: slack-sdk (>=3.17.2)
Requires-Dist: six (>=1.11.0)
